pollination_dash_io/AuthUser.py
pollination_dash_io/CreateStudy.py
pollination_dash_io/EpwMap.py
pollination_dash_io/GetAPIKey.py
pollination_dash_io/GetGeometry.py
pollination_dash_io/GetHbjson.py
pollination_dash_io/GetHost.py
pollination_dash_io/ManageSettings.py
pollination_dash_io/ReadLocalFile.py
pollination_dash_io/RecipeInputsForm.py
pollination_dash_io/RunCommand.py
pollination_dash_io/SelectAccount.py
pollination_dash_io/SelectCloudArtifact.py
pollination_dash_io/SelectProject.py
pollination_dash_io/SelectRecipe.py
pollination_dash_io/SelectRun.py
pollination_dash_io/SelectStudy.py
pollination_dash_io/SendGeometry.py
pollination_dash_io/SendHbjson.py
pollination_dash_io/SendResults.py
pollination_dash_io/StudyProgress.py
pollination_dash_io/__init__.py
pollination_dash_io/_imports_.py
pollination_dash_io/_utils.py
pollination_dash_io/metadata.json
pollination_dash_io/package-info.json
pollination_dash_io/pollination_dash_io.js
pollination_dash_io-1.13.1.dist-info/LICENSE
pollination_dash_io-1.13.1.dist-info/METADATA
pollination_dash_io-1.13.1.dist-info/WHEEL
pollination_dash_io-1.13.1.dist-info/top_level.txt
pollination_dash_io-1.13.1.dist-info/RECORD
