Metadata-Version: 2.1
Name: pollination-dash-io
Version: 1.13.1
Summary: Pollination input/output components for Dash to use with pollination apps
Home-page: https://github.com/pollination/pollination-dash-io
Author: Ladybug Tools <info@ladybug.tools>
Author-email: info@ladybug.tools
License: Apache-2.0
Classifier: Framework :: Dash
Requires-Python: >=3.7
License-File: LICENSE
Requires-Dist: dash (>=2.5.1)
